conllu_path/__init__.py
conllu_path/conllu.py
conllu_path/exception.py
conllu_path/expr_parser.py
conllu_path/node_data.py
conllu_path/node_id.py
conllu_path/search.py
conllu_path/search_evaluator.py
conllu_path/sentence.py
conllu_path/tree.py
conllu_path/utils.py
conllu_path-0.0.6.dist-info/METADATA
conllu_path-0.0.6.dist-info/WHEEL
conllu_path-0.0.6.dist-info/licenses/LICENSE
conllu_path-0.0.6.dist-info/RECORD
